odoo/addons/fleet_vehicle_stock/README.rst
odoo/addons/fleet_vehicle_stock/__init__.py
odoo/addons/fleet_vehicle_stock/__manifest__.py
odoo/addons/fleet_vehicle_stock/i18n/fleet_vehicle_stock.pot
odoo/addons/fleet_vehicle_stock/i18n/it.po
odoo/addons/fleet_vehicle_stock/i18n/pt_BR.po
odoo/addons/fleet_vehicle_stock/models/__init__.py
odoo/addons/fleet_vehicle_stock/models/fleet_vehicle.py
odoo/addons/fleet_vehicle_stock/models/fleet_vehicle_model.py
odoo/addons/fleet_vehicle_stock/models/product_product.py
odoo/addons/fleet_vehicle_stock/models/product_template.py
odoo/addons/fleet_vehicle_stock/models/stock_move.py
odoo/addons/fleet_vehicle_stock/models/stock_picking_type.py
odoo/addons/fleet_vehicle_stock/models/stock_production_lot.py
odoo/addons/fleet_vehicle_stock/readme/CONFIGURE.rst
odoo/addons/fleet_vehicle_stock/readme/CONTRIBUTORS.rst
odoo/addons/fleet_vehicle_stock/readme/CREDITS.rst
odoo/addons/fleet_vehicle_stock/readme/DESCRIPTION.rst
odoo/addons/fleet_vehicle_stock/readme/USAGE.rst
odoo/addons/fleet_vehicle_stock/static/description/icon.png
odoo/addons/fleet_vehicle_stock/static/description/index.html
odoo/addons/fleet_vehicle_stock/tests/__init__.py
odoo/addons/fleet_vehicle_stock/tests/test_fleet_vehicle.py
odoo/addons/fleet_vehicle_stock/views/fleet_vehicle.xml
odoo/addons/fleet_vehicle_stock/views/fleet_vehicle_model.xml
odoo/addons/fleet_vehicle_stock/views/product_product.xml
odoo/addons/fleet_vehicle_stock/views/product_template.xml
odoo/addons/fleet_vehicle_stock/views/stock_picking_type.xml
odoo/addons/fleet_vehicle_stock/views/stock_production_lot.xml
odoo12_addon_fleet_vehicle_stock-12.0.1.0.0.99.dev10.dist-info/METADATA
odoo12_addon_fleet_vehicle_stock-12.0.1.0.0.99.dev10.dist-info/WHEEL
odoo12_addon_fleet_vehicle_stock-12.0.1.0.0.99.dev10.dist-info/top_level.txt
odoo12_addon_fleet_vehicle_stock-12.0.1.0.0.99.dev10.dist-info/RECORD
